jupyterpower/__init__.py
jupyterpower/_version.py
jupyterpower/io.py
jupyterpower/model.py
jupyterpower/paths.py
jupyterpower/utils.py
jupyterpower/viz.py
jupyterpower-0.9.6.dist-info/licenses/LICENSE
jupyterpower-0.9.6.dist-info/METADATA
jupyterpower-0.9.6.dist-info/WHEEL
jupyterpower-0.9.6.dist-info/top_level.txt
jupyterpower-0.9.6.dist-info/RECORD
