Metadata-Version: 2.4
Name: jupyterpower
Version: 0.9.6
Summary: Utilities for Data Science using Python and Jupyter Notebook
Author: Bruce DeSimas
License: MIT
Project-URL: Homepage, https://github.com/bdesimas/JupyterPower
Project-URL: Source, https://github.com/bdesimas/JupyterPower
Project-URL: Issues, https://github.com/bdesimas/JupyterPower/issues
Project-URL: Documentation, https://github.com/bdesimas/JupyterPower#readme
Requires-Python: >=3.10
License-File: LICENSE
Requires-Dist: pandas>=2.2
Requires-Dist: matplotlib>=3.8
Requires-Dist: scikit-learn>=1.5
Dynamic: license-file
